pynitevolumes/mesh/__init__.py
pynitevolumes/mesh/_array_types.py
pynitevolumes/mesh/base_struct.py
pynitevolumes/mesh/cartesian.py
pynitevolumes/mesh/disc.py
pynitevolumes/mesh/md.py
pynitevolumes/mesh/mesh_io.py
pynitevolumes/mesh/meshtools.py
pynitevolumes/mesh/plotting.py
pynitevolumes/mesh/py.typed
pynitevolumes/schemes/mesh_dir/dmesh1/dmesh1_0.pvm
pynitevolumes/schemes/mesh_dir/dmesh1/dmesh1_1.pvm
pynitevolumes/schemes/mesh_dir/dmesh1/dmesh1_2.pvm
pynitevolumes/schemes/mesh_dir/dmesh1/dmesh1_3.pvm
pynitevolumes/schemes/mesh_dir/dmesh1/dmesh1_4.pvm
pynitevolumes/schemes/mesh_dir/mesh1/mesh1_0.pvm
pynitevolumes/schemes/mesh_dir/mesh1/mesh1_1.pvm
pynitevolumes/schemes/mesh_dir/mesh1/mesh1_2.pvm
pynitevolumes/schemes/mesh_dir/mesh1/mesh1_3.pvm
pynitevolumes/schemes/mesh_dir/mesh1/mesh1_4.pvm
pynitevolumes/schemes/mesh_dir/mesh1/mesh1_5.pvm
pynitevolumes/schemes/mesh_dir/mesh1/mesh1_6.pvm
pynitevolumes/schemes/mesh_dir/mesh1/mesh1_7.pvm
pynitevolumes/schemes/mesh_dir/mesh1_disk/mesh1_disk_0.pvm
pynitevolumes/schemes/mesh_dir/mesh1_disk/mesh1_disk_1.pvm
pynitevolumes/schemes/mesh_dir/mesh1_disk/mesh1_disk_2.pvm
pynitevolumes/schemes/mesh_dir/mesh1_disk/mesh1_disk_3.pvm
pynitevolumes/schemes/mesh_dir/mesh1_disk/mesh1_disk_4.pvm
pynitevolumes/schemes/mesh_dir/rect4/rect4_0.pvm
pynitevolumes/schemes/mesh_dir/rect4/rect4_1.pvm
pynitevolumes/schemes/mesh_dir/rect4/rect4_2.pvm
pynitevolumes/schemes/mesh_dir/rect4/rect4_3.pvm
pynitevolumes/schemes/mesh_dir/rect4/rect4_4.pvm
pynitevolumes/schemes/mesh_dir/rect4/rect4_5.pvm
pynitevolumes/schemes/mesh_dir/rect4/rect4_6.pvm
pynitevolumes/schemes/mesh_dir/rect4/rect4_7.pvm
pynitevolumes/schemes/mesh_dir/rect_disk/rect_disk_0.pvm
pynitevolumes/schemes/mesh_dir/rect_disk/rect_disk_1.pvm
pynitevolumes/schemes/mesh_dir/rect_disk/rect_disk_2.pvm
pynitevolumes/schemes/mesh_dir/rect_disk/rect_disk_3.pvm
pynitevolumes/schemes/mesh_dir/rect_disk/rect_disk_4.pvm
pynitevolumes/schemes/tpfa/__init__.py
pynitevolumes_edu-0.0.3.dist-info/METADATA
pynitevolumes_edu-0.0.3.dist-info/WHEEL
pynitevolumes_edu-0.0.3.dist-info/entry_points.txt
pynitevolumes_edu-0.0.3.dist-info/top_level.txt
pynitevolumes_edu-0.0.3.dist-info/RECORD
